flatjsondict/__init__.py
flatjsondict/flatjsondict.py
flatjsondict-1.2.2.dist-info/LICENSE
flatjsondict-1.2.2.dist-info/METADATA
flatjsondict-1.2.2.dist-info/WHEEL
flatjsondict-1.2.2.dist-info/RECORD
