Metadata-Version: 2.1
Name: flatjsondict
Version: 1.2.2
Summary: JSON-like data manipulation and transformation to and from nested parent-child and flat label-value data items.
Home-page: https://gitlab.com/martins-bruvelis/flatjsondict
Author: Martins Bruvelis
Author-email: martins.bruvelis@gmail.com
Requires-Python: >=3.7,<4.0
Classifier: Programming Language :: Python :: 3
Classifier: Programming Language :: Python :: 3.7
Classifier: Programming Language :: Python :: 3.8
Classifier: Programming Language :: Python :: 3.9
Classifier: Programming Language :: Python :: 3.10
Classifier: Programming Language :: Python :: 3.11
Classifier: Programming Language :: Python :: 3.12
Project-URL: Documentation, https://gitlab.com/martins-bruvelis/flatjsondict/-/blob/main/README.md
Project-URL: Repository, https://gitlab.com/martins-bruvelis/flatjsondict
